nonebot_plugin_cyberfurry/__init__.py
nonebot_plugin_cyberfurry/callapi.py
nonebot_plugin_cyberfurry/config.py
nonebot_plugin_cyberfurry/cyberauto.py
nonebot_plugin_cyberfurry/cyberfurry.py
nonebot_plugin_cyberfurry/cyberfurrymodel.py
nonebot_plugin_cyberfurry/cyberhistory.py
nonebot_plugin_cyberfurry/cyberinit.py
nonebot_plugin_cyberfurry/cyberlife.py
nonebot_plugin_cyberfurry/data_source.py
nonebot_plugin_cyberfurry/jsondata.py
nonebot_plugin_cyberfurry/plugins_data.py
nonebot_plugin_cyberfurry-1.6.3.dist-info/LICENSE
nonebot_plugin_cyberfurry-1.6.3.dist-info/METADATA
nonebot_plugin_cyberfurry-1.6.3.dist-info/WHEEL
nonebot_plugin_cyberfurry-1.6.3.dist-info/top_level.txt
nonebot_plugin_cyberfurry-1.6.3.dist-info/RECORD
