Metadata-Version: 2.1
Name: nonebot-plugin-cyberfurry
Version: 1.6.3
Summary: nonebot插件 cyberfurry-与赛博狼狼对话吧~
Author: cubstaryow
Author-email: cub_staryow@outlook.com
License: GNU GENERAL PUBLIC LICENSE
Project-URL: repository, https://github.com/cubstaryow/nonebot-plugin-cyberfurry
Keywords: egg,bacon,sausage,tomatoes,Lobster Thermidor
Classifier: Development Status :: 4 - Beta
Classifier: Programming Language :: Python
Requires-Python: >=3.10
License-File: LICENSE
Requires-Dist: nonebot-adapter-onebot
Requires-Dist: nonebot2
Requires-Dist: nonebot-plugin-localstore
Requires-Dist: nonebot-plugin-apscheduler
Requires-Dist: aiohttp
